README.rst
setup.py
sqlitemodel/Database.py
sqlitemodel/Model.py
sqlitemodel/SQL.py
sqlitemodel/__init__.py
sqlitemodel.egg-info/PKG-INFO
sqlitemodel.egg-info/SOURCES.txt
sqlitemodel.egg-info/dependency_links.txt
sqlitemodel.egg-info/top_level.txt